{"stage": 19, "type": "road", "Stg": ["Primoz Roglic", "Geraint Thomas", "Romain Bardet", "Daniel Martin", "Rafa\u0142 Majka", "Tom Dumoulin", "Mikel Landa", "Christopher Froome", "Steven Kruijswijk", "Ilnur Zakarin", "Gorka Izagirre", "Bob Jungels", "Egan Arley Bernal", "Domenico Pozzovivo", "Ion Izagirre"], "GC": ["Geraint Thomas", "Tom Dumoulin", "Primoz Roglic", "Christopher Froome", "Steven Kruijswijk", "Mikel Landa", "Romain Bardet", "Daniel Martin", "Nairo Quintana", "Ilnur Zakarin", "Bob Jungels", "Jakob Fuglsang", "Pierre Latour", "Alejandro Valverde", "Egan Arley Bernal", "Tanel Kangert", "Warren Barguil", "Domenico Pozzovivo", "Rafa\u0142 Majka", "Guillaume Martin"], "PC": ["Peter Sagan", "Alexander Kristoff", "Arnaud D\u00e9mare", "John Degenkolb", "Julian Alaphilippe", "Greg Van Avermaet"], "KOM": ["Julian Alaphilippe", "Warren Barguil", "Rafa\u0142 Majka", "Geraint Thomas", "Tom Dumoulin", "Primoz Roglic"], "Spr": ["Damien Gaudin", "Daniele Bennati", "Tom-Jelte Slagter", "Marcus Burghardt", "Lukas P\u00f6stlberger", "Bauke Mollema", "Julian Alaphilippe", "Arthur Vichot", "Tanel Kangert", "Warren Barguil"], "Sum": {"hc": [["Julian Alaphilippe", "Mikel Nieve", "Bob Jungels", "Warren Barguil", "Tanel Kangert", "Gorka Izagirre", "Rafa\u0142 Majka", "Andrey Amador"], ["Rafa\u0142 Majka", "Primoz Roglic", "Tom Dumoulin", "Geraint Thomas", "Mikel Landa", "Romain Bardet", "Daniel Martin", "Steven Kruijswijk"]], "cat1": [["Julian Alaphilippe", "Warren Barguil", "Bauke Mollema", "Tanel Kangert", "Bob Jungels"]]}, "Bky": ["Daniele Bennati", "Tom-Jelte Slagter", "Bauke Mollema", "Julian Alaphilippe", "Tanel Kangert", "Warren Barguil", "Adam Yates", "Gorka Izagirre", "Mikel Nieve", "Bob Jungels", "Andrey Amador"], "Ass": {"TC": ["MOV", "TBM", "SKY"]}, "abandons": ["Luis Leon Sanchez", "Tsgabu Grmay", "Axel Domont", "Robert Ki\u0161erlovski", "Michael Matthews", "Tiesj Benoot", "Richie Porte", "Jos\u00e9 Joaqu\u00edn Rojas", "Tony Martin", "Alexis Vuillermoz", "Jens Keukeleire", "Mark Cavendish", "Marcel Kittel", "Mark Renshaw", "Tony Gallopin", "Fernando Gaviria", "Rick Zabel", "Dylan Groenewegen", "Andr\u00e9 Greipel", "Marcel Sieberg", "Rigoberto Uran", "Dmitriy Gruzdev", "Rein Taaram\u00e4e", "Vincenzo Nibali", "Patrick Bevin", "Gianni Moscon", "Tim Declercq", "Serge Pauwels", "Damien Howson", "Philippe Gilbert", "Jelle Vanendert"]}