{
  "stage": 4,
  "type": "road",
  "Stg": [
    "Elia Viviani",
    "Alexander Kristoff",
    "Caleb Ewan",
    "Peter Sagan",
    "Dylan Groenewegen",
    "Mike Teunissen",
    "Giacomo Nizzolo",
    "Jasper Stuyven",
    "Michael Matthews",
    "Christophe Laporte",
    "Matteo Trentin",
    "André Greipel",
    "Niccolò Bonifazio",
    "Matej Mohorič",
    "Iván Cortina"
  ],
  "GC": [
    "Julian Alaphilippe",
    "Wout van Aert",
    "Steven Kruijswijk",
    "George Bennett",
    "Michael Matthews",
    "Egan Bernal",
    "Geraint Thomas",
    "Enric Mas",
    "Greg Van Avermaet",
    "Michael Woods",
    "Wilco Kelderman",
    "Thibaut Pinot",
    "Rigoberto Urán",
    "Tejay van Garderen",
    "Sonny Colbrelli",
    "David Gaudu",
    "Rudy Molard",
    "Peter Sagan",
    "Nicholas Roche",
    "Matteo Trentin"
  ],
  "PC": [
    "Peter Sagan",
    "Elia Viviani",
    "Michael Matthews",
    "Sonny Colbrelli",
    "Mike Teunissen",
    "Matteo Trentin"
  ],
  "KOM": [
    "Tim Wellens",
    "Xandro Meurisse",
    "Greg Van Avermaet",
    "Michael Schär",
    "Wilco Kelderman",
    "Julian Alaphilippe"
  ],
  "Spr": [
    "Frederik Backaert",
    "Michael Schär",
    "Yoann Offredo",
    "Elia Viviani",
    "Sonny Colbrelli",
    "Peter Sagan",
    "Matteo Trentin",
    "Michael Matthews",
    "Michael Mørkøv",
    "Andrea Pasqualon"
  ],
  "Sum": {
    "hc": [],
    "cat1": []
  },
  "Bky": [
    "Frederik Backaert",
    "Michael Schär",
    "Yoann Offredo"
  ],
  "Ass": {
    "TC": [
      "TJV",
      "SUN",
      "EF1"
    ]
  },
  "abandons": []
}